suitcase/jsonl/__init__.py
suitcase/jsonl/_version.py
suitcase/jsonl/tests/__init__.py
suitcase/jsonl/tests/conftest.py
suitcase/jsonl/tests/tests.py
suitcase_jsonl-0.2.2.dist-info/LICENSE
suitcase_jsonl-0.2.2.dist-info/METADATA
suitcase_jsonl-0.2.2.dist-info/WHEEL
suitcase_jsonl-0.2.2.dist-info/entry_points.txt
suitcase_jsonl-0.2.2.dist-info/top_level.txt
suitcase_jsonl-0.2.2.dist-info/RECORD
