Metadata-Version: 2.1
Name: suitcase-jsonl
Version: 0.2.2
Summary: UNKNOWN
Home-page: UNKNOWN
License: BSD (3-clause)
Platform: UNKNOWN
Classifier: Development Status :: 2 - Pre-Alpha
Classifier: Natural Language :: English
Classifier: Programming Language :: Python :: 3.6
License-File: LICENSE
Requires-Dist: event-model (>=1.8.0rc1)
Requires-Dist: suitcase-utils
